MANIFEST.in
README.rst
setup.py
flask_appconfig/__init__.py
flask_appconfig/cli.py
flask_appconfig/env.py
flask_appconfig/heroku.py
flask_appconfig/server_backends.py
flask_appconfig/util.py
flask_appconfig.egg-info/PKG-INFO
flask_appconfig.egg-info/SOURCES.txt
flask_appconfig.egg-info/dependency_links.txt
flask_appconfig.egg-info/entry_points.txt
flask_appconfig.egg-info/requires.txt
flask_appconfig.egg-info/top_level.txt