Metadata-Version: 1.1
Name: flask-appconfig
Version: 0.11.0
Summary: Configures Flask applications in a canonical way. Also auto-configures Heroku. Aims to standardize configuration.
Home-page: http://github.com/mbr/flask-appconfig
Author: Marc Brinkmann
Author-email: git@marcbrinkmann.de
License: MIT
Platform: UNKNOWN
Classifier: Programming Language :: Python :: 2
Classifier: Programming Language :: Python :: 3
